<annotation>
	<folder>JPGimg</folder>
	<filename>000254.jpg</filename>
	<path>F:\COCOdata\JPGimg\000254.jpg</path>
	<source>
		<database>Unknown</database>
	</source>
	<size>
		<width>614</width>
		<height>303</height>
		<depth>3</depth>
	</size>
	<segmented>0</segmented>
	<object>
		<name>Accumulation Flow</name>
		<pose>Unspecified</pose>
		<truncated>0</truncated>
		<difficult>0</difficult>
		<bndbox>
			<xmin>6</xmin>
			<ymin>10</ymin>
			<xmax>582</xmax>
			<ymax>135</ymax>
		</bndbox>
	</object>
	<object>
		<name>Volume</name>
		<pose>Unspecified</pose>
		<truncated>0</truncated>
		<difficult>0</difficult>
		<bndbox>
			<xmin>4</xmin>
			<ymin>142</ymin>
			<xmax>613</xmax>
			<ymax>280</ymax>
		</bndbox>
	</object>
</annotation>
