<annotation>
	<folder>JPGimg</folder>
	<filename>000887.jpg</filename>
	<path>F:\COCOdata\JPGimg\000887.jpg</path>
	<source>
		<database>Unknown</database>
	</source>
	<size>
		<width>927</width>
		<height>449</height>
		<depth>3</depth>
	</size>
	<segmented>0</segmented>
	<object>
		<name>Flow</name>
		<pose>Unspecified</pose>
		<truncated>0</truncated>
		<difficult>0</difficult>
		<bndbox>
			<xmin>43</xmin>
			<ymin>51</ymin>
			<xmax>875</xmax>
			<ymax>214</ymax>
		</bndbox>
	</object>
	<object>
		<name>Leakage Volume</name>
		<pose>Unspecified</pose>
		<truncated>0</truncated>
		<difficult>0</difficult>
		<bndbox>
			<xmin>16</xmin>
			<ymin>254</ymin>
			<xmax>882</xmax>
			<ymax>400</ymax>
		</bndbox>
	</object>
</annotation>
