<annotation>
	<folder>JPGimg</folder>
	<filename>001597.jpg</filename>
	<path>F:\COCOdata\JPGimg\001597.jpg</path>
	<source>
		<database>Unknown</database>
	</source>
	<size>
		<width>558</width>
		<height>272</height>
		<depth>3</depth>
	</size>
	<segmented>0</segmented>
	<object>
		<name>Premature_cycling Flow</name>
		<pose>Unspecified</pose>
		<truncated>0</truncated>
		<difficult>0</difficult>
		<bndbox>
			<xmin>86</xmin>
			<ymin>41</ymin>
			<xmax>530</xmax>
			<ymax>126</ymax>
		</bndbox>
	</object>
	<object>
		<name>Premature_cycling Volume</name>
		<pose>Unspecified</pose>
		<truncated>0</truncated>
		<difficult>0</difficult>
		<bndbox>
			<xmin>80</xmin>
			<ymin>164</ymin>
			<xmax>542</xmax>
			<ymax>239</ymax>
		</bndbox>
	</object>
</annotation>
