<annotation>
	<folder>JPGimg</folder>
	<filename>001842.jpg</filename>
	<path>F:\COCOdata\JPGimg\001842.jpg</path>
	<source>
		<database>Unknown</database>
	</source>
	<size>
		<width>407</width>
		<height>201</height>
		<depth>3</depth>
	</size>
	<segmented>0</segmented>
	<object>
		<name>Flow</name>
		<pose>Unspecified</pose>
		<truncated>0</truncated>
		<difficult>0</difficult>
		<bndbox>
			<xmin>69</xmin>
			<ymin>25</ymin>
			<xmax>401</xmax>
			<ymax>87</ymax>
		</bndbox>
	</object>
	<object>
		<name>Leakage Volume</name>
		<pose>Unspecified</pose>
		<truncated>0</truncated>
		<difficult>0</difficult>
		<bndbox>
			<xmin>24</xmin>
			<ymin>106</ymin>
			<xmax>379</xmax>
			<ymax>183</ymax>
		</bndbox>
	</object>
</annotation>
