<annotation>
	<folder>JPGimg</folder>
	<filename>001881.jpg</filename>
	<path>F:\COCOdata\JPGimg\001881.jpg</path>
	<source>
		<database>Unknown</database>
	</source>
	<size>
		<width>449</width>
		<height>334</height>
		<depth>3</depth>
	</size>
	<segmented>0</segmented>
	<object>
		<name>Premature_cycling Flow</name>
		<pose>Unspecified</pose>
		<truncated>0</truncated>
		<difficult>0</difficult>
		<bndbox>
			<xmin>58</xmin>
			<ymin>101</ymin>
			<xmax>409</xmax>
			<ymax>173</ymax>
		</bndbox>
	</object>
	<object>
		<name>Premature_cycling Volume</name>
		<pose>Unspecified</pose>
		<truncated>0</truncated>
		<difficult>0</difficult>
		<bndbox>
			<xmin>10</xmin>
			<ymin>223</ymin>
			<xmax>361</xmax>
			<ymax>330</ymax>
		</bndbox>
	</object>
</annotation>
