<annotation>
	<folder>JPGimg</folder>
	<filename>001818.jpg</filename>
	<path>F:\COCOdata\JPGimg\001818.jpg</path>
	<source>
		<database>Unknown</database>
	</source>
	<size>
		<width>1083</width>
		<height>628</height>
		<depth>3</depth>
	</size>
	<segmented>0</segmented>
	<object>
		<name>Double_Triggering Volume</name>
		<pose>Unspecified</pose>
		<truncated>0</truncated>
		<difficult>0</difficult>
		<bndbox>
			<xmin>50</xmin>
			<ymin>488</ymin>
			<xmax>984</xmax>
			<ymax>594</ymax>
		</bndbox>
	</object>
	<object>
		<name>Double_Triggering Flow</name>
		<pose>Unspecified</pose>
		<truncated>0</truncated>
		<difficult>0</difficult>
		<bndbox>
			<xmin>79</xmin>
			<ymin>217</ymin>
			<xmax>979</xmax>
			<ymax>344</ymax>
		</bndbox>
	</object>
</annotation>
