<annotation>
	<folder>JPGimg</folder>
	<filename>002065.jpg</filename>
	<path>F:\COCOdata\JPGimg\002065.jpg</path>
	<source>
		<database>Unknown</database>
	</source>
	<size>
		<width>748</width>
		<height>316</height>
		<depth>3</depth>
	</size>
	<segmented>0</segmented>
	<object>
		<name>Ineffective_effort Flow</name>
		<pose>Unspecified</pose>
		<truncated>0</truncated>
		<difficult>0</difficult>
		<bndbox>
			<xmin>127</xmin>
			<ymin>23</ymin>
			<xmax>734</xmax>
			<ymax>113</ymax>
		</bndbox>
	</object>
	<object>
		<name>Ineffective_effort Volume</name>
		<pose>Unspecified</pose>
		<truncated>0</truncated>
		<difficult>0</difficult>
		<bndbox>
			<xmin>56</xmin>
			<ymin>230</ymin>
			<xmax>651</xmax>
			<ymax>302</ymax>
		</bndbox>
	</object>
</annotation>
