<annotation>
	<folder>JPGimg</folder>
	<filename>002452.jpg</filename>
	<path>F:\COCOdata\JPGimg\002452.jpg</path>
	<source>
		<database>Unknown</database>
	</source>
	<size>
		<width>416</width>
		<height>175</height>
		<depth>3</depth>
	</size>
	<segmented>0</segmented>
	<object>
		<name>Ineffective_effort Flow</name>
		<pose>Unspecified</pose>
		<truncated>0</truncated>
		<difficult>0</difficult>
		<bndbox>
			<xmin>62</xmin>
			<ymin>16</ymin>
			<xmax>412</xmax>
			<ymax>70</ymax>
		</bndbox>
	</object>
	<object>
		<name>Ineffective_effort Volume</name>
		<pose>Unspecified</pose>
		<truncated>0</truncated>
		<difficult>0</difficult>
		<bndbox>
			<xmin>23</xmin>
			<ymin>84</ymin>
			<xmax>389</xmax>
			<ymax>173</ymax>
		</bndbox>
	</object>
</annotation>
