<annotation>
	<folder>JPGimg</folder>
	<filename>002663.jpg</filename>
	<path>F:\COCOdata\JPGimg\002663.jpg</path>
	<source>
		<database>Unknown</database>
	</source>
	<size>
		<width>520</width>
		<height>231</height>
		<depth>3</depth>
	</size>
	<segmented>0</segmented>
	<object>
		<name>Normal Flow</name>
		<pose>Unspecified</pose>
		<truncated>0</truncated>
		<difficult>0</difficult>
		<bndbox>
			<xmin>51</xmin>
			<ymin>24</ymin>
			<xmax>506</xmax>
			<ymax>98</ymax>
		</bndbox>
	</object>
	<object>
		<name>Normal Volume</name>
		<pose>Unspecified</pose>
		<truncated>0</truncated>
		<difficult>0</difficult>
		<bndbox>
			<xmin>93</xmin>
			<ymin>157</ymin>
			<xmax>510</xmax>
			<ymax>216</ymax>
		</bndbox>
	</object>
</annotation>
